nose_parameterized/__init__.py
nose_parameterized/compat.py
nose_parameterized/parameterized.py
nose_parameterized/test.py
nose_parameterized-0.5.0.dist-info/DESCRIPTION.rst
nose_parameterized-0.5.0.dist-info/METADATA
nose_parameterized-0.5.0.dist-info/metadata.json
nose_parameterized-0.5.0.dist-info/RECORD
nose_parameterized-0.5.0.dist-info/top_level.txt
nose_parameterized-0.5.0.dist-info/WHEEL
