Metadata-Version: 1.0
Name: nose-parameterized
Version: 0.5.0
Summary: Parameterized testing with any Python test framework
Home-page: https://github.com/wolever/nose-parameterized
Author: David Wolever
Author-email: david@wolever.net
License: UNKNOWN
Platform: UNKNOWN
Classifier: Programming Language :: Python
Classifier: Programming Language :: Python :: 3
Classifier: License :: OSI Approved :: BSD License
